{
  "blocks": [
{"x": "0","y": "475","width": "45","height": "23","color": "red","score": "10","sprite": ""},
{"x": "46","y": "475","width": "45","height": "23","color": "red","score": "10","sprite": ""},
{"x": "92","y": "475","width": "45","height": "23","color": "red","score": "10","sprite": ""},
{"x": "138","y": "475","width": "45","height": "23","color": "red","score": "10","sprite": ""},
{"x": "184","y": "475","width": "45","height": "23","color": "red","score": "10","sprite": ""},
{"x": "230","y": "475","width": "45","height": "23","color": "red","score": "10","sprite": ""},
{"x": "276","y": "475","width": "45","height": "23","color": "red","score": "10","sprite": ""},
{"x": "322","y": "475","width": "45","height": "23","color": "red","score": "10","sprite": ""},
{"x": "368","y": "475","width": "45","height": "23","color": "red","score": "10","sprite": ""},
{"x": "414","y": "475","width": "45","height": "23","color": "red","score": "10","sprite": ""},
{"x": "460","y": "475","width": "45","height": "23","color": "red","score": "10","sprite": ""},
{"x": "506","y": "475","width": "45","height": "23","color": "red","score": "10","sprite": ""},
{"x": "552","y": "475","width": "45","height": "23","color": "red","score": "10","sprite": ""},
{"x": "598","y": "475","width": "45","height": "23","color": "red","score": "10","sprite": ""},
{"x": "644","y": "475","width": "45","height": "23","color": "red","score": "10","sprite": ""},
{"x": "690","y": "475","width": "45","height": "23","color": "red","score": "10","sprite": ""},
{"x": "736","y": "475","width": "45","height": "23","color": "red","score": "10","sprite": ""},
{"x": "782","y": "475","width": "45","height": "23","color": "red","score": "10","sprite": ""},
{"x": "828","y": "475","width": "45","height": "23","color": "red","score": "10","sprite": ""},
{"x": "874","y": "475","width": "45","height": "23","color": "red","score": "10","sprite": ""},

{"x": "0","y": "400","width": "45","height": "23","color": "orange","score": "25","sprite": ""},
{"x": "46","y": "400","width": "45","height": "23","color": "orange","score": "25","sprite": ""},
{"x": "92","y": "400","width": "45","height": "23","color": "orange","score": "25","sprite": ""},
{"x": "138","y": "400","width": "45","height": "23","color": "orange","score": "25","sprite": ""},
{"x": "184","y": "400","width": "45","height": "23","color": "orange","score": "25","sprite": ""},
{"x": "230","y": "400","width": "45","height": "23","color": "orange","score": "25","sprite": ""},
{"x": "276","y": "400","width": "45","height": "23","color": "orange","score": "25","sprite": ""},
{"x": "322","y": "400","width": "45","height": "23","color": "orange","score": "25","sprite": ""},
{"x": "368","y": "400","width": "45","height": "23","color": "orange","score": "25","sprite": ""},
{"x": "414","y": "400","width": "45","height": "23","color": "orange","score": "25","sprite": ""},
{"x": "460","y": "400","width": "45","height": "23","color": "orange","score": "25","sprite": ""},
{"x": "506","y": "400","width": "45","height": "23","color": "orange","score": "25","sprite": ""},
{"x": "552","y": "400","width": "45","height": "23","color": "orange","score": "25","sprite": ""},
{"x": "598","y": "400","width": "45","height": "23","color": "orange","score": "25","sprite": ""},
{"x": "644","y": "400","width": "45","height": "23","color": "orange","score": "25","sprite": ""},
{"x": "690","y": "400","width": "45","height": "23","color": "orange","score": "25","sprite": ""},
{"x": "736","y": "400","width": "45","height": "23","color": "orange","score": "25","sprite": ""},
{"x": "782","y": "400","width": "45","height": "23","color": "orange","score": "25","sprite": ""},
{"x": "828","y": "400","width": "45","height": "23","color": "orange","score": "25","sprite": ""},
{"x": "874","y": "400","width": "45","height": "23","color": "orange","score": "25","sprite": ""},
{"x": "0","y": "376","width": "45","height": "23","color": "yellow","score": "50","sprite": ""},
{"x": "46","y": "376","width": "45","height": "23","color": "yellow","score": "50","sprite": ""},
{"x": "92","y": "376","width": "45","height": "23","color": "yellow","score": "50","sprite": ""},
{"x": "138","y": "376","width": "45","height": "23","color": "yellow","score": "50","sprite": ""},
{"x": "184","y": "376","width": "45","height": "23","color": "yellow","score": "50","sprite": ""},
{"x": "230","y": "376","width": "45","height": "23","color": "yellow","score": "50","sprite": ""},
{"x": "276","y": "376","width": "45","height": "23","color": "yellow","score": "50","sprite": ""},
{"x": "322","y": "376","width": "45","height": "23","color": "yellow","score": "50","sprite": ""},
{"x": "368","y": "376","width": "45","height": "23","color": "yellow","score": "50","sprite": ""},
{"x": "414","y": "376","width": "45","height": "23","color": "yellow","score": "50","sprite": ""},
{"x": "460","y": "376","width": "45","height": "23","color": "yellow","score": "50","sprite": ""},
{"x": "506","y": "376","width": "45","height": "23","color": "yellow","score": "50","sprite": ""},
{"x": "552","y": "376","width": "45","height": "23","color": "yellow","score": "50","sprite": ""},
{"x": "598","y": "376","width": "45","height": "23","color": "yellow","score": "50","sprite": ""},
{"x": "644","y": "376","width": "45","height": "23","color": "yellow","score": "50","sprite": ""},
{"x": "690","y": "376","width": "45","height": "23","color": "yellow","score": "50","sprite": ""},
{"x": "736","y": "376","width": "45","height": "23","color": "yellow","score": "50","sprite": ""},
{"x": "782","y": "376","width": "45","height": "23","color": "yellow","score": "50","sprite": ""},
{"x": "828","y": "376","width": "45","height": "23","color": "yellow","score": "50","sprite": ""},
{"x": "874","y": "376","width": "45","height": "23","color": "yellow","score": "50","sprite": ""},
  
{"x": "0","y": "300","width": "45","height": "23","color": "green","score": "75","sprite": ""},
{"x": "46","y": "300","width": "45","height": "23","color": "green","score": "75","sprite": ""},
{"x": "92","y": "300","width": "45","height": "23","color": "green","score": "75","sprite": ""},
{"x": "138","y": "300","width": "45","height": "23","color": "green","score": "75","sprite": ""},
{"x": "184","y": "300","width": "45","height": "23","color": "green","score": "75","sprite": ""},
{"x": "230","y": "300","width": "45","height": "23","color": "green","score": "75","sprite": ""},
{"x": "276","y": "300","width": "45","height": "23","color": "green","score": "75","sprite": ""},
{"x": "322","y": "300","width": "45","height": "23","color": "green","score": "75","sprite": ""},
{"x": "368","y": "300","width": "45","height": "23","color": "green","score": "75","sprite": ""},
{"x": "414","y": "300","width": "45","height": "23","color": "green","score": "75","sprite": ""},
{"x": "460","y": "300","width": "45","height": "23","color": "green","score": "75","sprite": ""},
{"x": "506","y": "300","width": "45","height": "23","color": "green","score": "75","sprite": ""},
{"x": "552","y": "300","width": "45","height": "23","color": "green","score": "75","sprite": ""},
{"x": "598","y": "300","width": "45","height": "23","color": "green","score": "75","sprite": ""},
{"x": "644","y": "300","width": "45","height": "23","color": "green","score": "75","sprite": ""},
{"x": "690","y": "300","width": "45","height": "23","color": "green","score": "75","sprite": ""},
{"x": "736","y": "300","width": "45","height": "23","color": "green","score": "75","sprite": ""},
{"x": "782","y": "300","width": "45","height": "23","color": "green","score": "75","sprite": ""},
{"x": "828","y": "300","width": "45","height": "23","color": "green","score": "75","sprite": ""},
{"x": "874","y": "300","width": "45","height": "23","color": "green","score": "75","sprite": ""},
{"x": "0","y": "276","width": "45","height": "23","color": "blue","score": "100","sprite": ""},
{"x": "46","y": "276","width": "45","height": "23","color": "blue","score": "100","sprite": ""},
{"x": "92","y": "276","width": "45","height": "23","color": "blue","score": "100","sprite": ""},
{"x": "138","y": "276","width": "45","height": "23","color": "blue","score": "100","sprite": ""},
{"x": "184","y": "276","width": "45","height": "23","color": "blue","score": "100","sprite": ""},
{"x": "230","y": "276","width": "45","height": "23","color": "blue","score": "100","sprite": ""},
{"x": "276","y": "276","width": "45","height": "23","color": "blue","score": "100","sprite": ""},
{"x": "322","y": "276","width": "45","height": "23","color": "blue","score": "100","sprite": ""},
{"x": "368","y": "276","width": "45","height": "23","color": "blue","score": "100","sprite": ""},
{"x": "414","y": "276","width": "45","height": "23","color": "blue","score": "100","sprite": ""},
{"x": "460","y": "276","width": "45","height": "23","color": "blue","score": "100","sprite": ""},
{"x": "506","y": "276","width": "45","height": "23","color": "blue","score": "100","sprite": ""},
{"x": "552","y": "276","width": "45","height": "23","color": "blue","score": "100","sprite": ""},
{"x": "598","y": "276","width": "45","height": "23","color": "blue","score": "100","sprite": ""},
{"x": "644","y": "276","width": "45","height": "23","color": "blue","score": "100","sprite": ""},
{"x": "690","y": "276","width": "45","height": "23","color": "blue","score": "100","sprite": ""},
{"x": "736","y": "276","width": "45","height": "23","color": "blue","score": "100","sprite": ""},
{"x": "782","y": "276","width": "45","height": "23","color": "blue","score": "100","sprite": ""},
{"x": "828","y": "276","width": "45","height": "23","color": "blue","score": "100","sprite": ""},
{"x": "874","y": "276","width": "45","height": "23","color": "blue","score": "100","sprite": ""},
  
{"x": "0","y": "200","width": "45","height": "23","color": "indigo","score": "125","sprite": ""},
{"x": "46","y": "200","width": "45","height": "23","color": "indigo","score": "125","sprite": ""},
{"x": "92","y": "200","width": "45","height": "23","color": "indigo","score": "125","sprite": ""},
{"x": "138","y": "200","width": "45","height": "23","color": "indigo","score": "125","sprite": ""},
{"x": "184","y": "200","width": "45","height": "23","color": "indigo","score": "125","sprite": ""},
{"x": "230","y": "200","width": "45","height": "23","color": "indigo","score": "125","sprite": ""},
{"x": "276","y": "200","width": "45","height": "23","color": "indigo","score": "125","sprite": ""},
{"x": "322","y": "200","width": "45","height": "23","color": "indigo","score": "125","sprite": ""},
{"x": "368","y": "200","width": "45","height": "23","color": "indigo","score": "125","sprite": ""},
{"x": "414","y": "200","width": "45","height": "23","color": "indigo","score": "125","sprite": ""},
{"x": "460","y": "200","width": "45","height": "23","color": "indigo","score": "125","sprite": ""},
{"x": "506","y": "200","width": "45","height": "23","color": "indigo","score": "125","sprite": ""},
{"x": "552","y": "200","width": "45","height": "23","color": "indigo","score": "125","sprite": ""},
{"x": "598","y": "200","width": "45","height": "23","color": "indigo","score": "125","sprite": ""},
{"x": "644","y": "200","width": "45","height": "23","color": "indigo","score": "125","sprite": ""},
{"x": "690","y": "200","width": "45","height": "23","color": "indigo","score": "125","sprite": ""},
{"x": "736","y": "200","width": "45","height": "23","color": "indigo","score": "125","sprite": ""},
{"x": "782","y": "200","width": "45","height": "23","color": "indigo","score": "125","sprite": ""},
{"x": "828","y": "200","width": "45","height": "23","color": "indigo","score": "125","sprite": ""},
{"x": "874","y": "200","width": "45","height": "23","color": "indigo","score": "125","sprite": ""},
{"x": "0","y": "176","width": "45","height": "23","color": "violet","score": "150","sprite": ""},
{"x": "46","y": "176","width": "45","height": "23","color": "violet","score": "150","sprite": ""},
{"x": "92","y": "176","width": "45","height": "23","color": "violet","score": "150","sprite": ""},
{"x": "138","y": "176","width": "45","height": "23","color": "violet","score": "150","sprite": ""},
{"x": "184","y": "176","width": "45","height": "23","color": "violet","score": "150","sprite": ""},
{"x": "230","y": "176","width": "45","height": "23","color": "violet","score": "150","sprite": ""},
{"x": "276","y": "176","width": "45","height": "23","color": "violet","score": "150","sprite": ""},
{"x": "322","y": "176","width": "45","height": "23","color": "violet","score": "150","sprite": ""},
{"x": "368","y": "176","width": "45","height": "23","color": "violet","score": "150","sprite": ""},
{"x": "414","y": "176","width": "45","height": "23","color": "violet","score": "150","sprite": ""},
{"x": "460","y": "176","width": "45","height": "23","color": "violet","score": "150","sprite": ""},
{"x": "506","y": "176","width": "45","height": "23","color": "violet","score": "150","sprite": ""},
{"x": "552","y": "176","width": "45","height": "23","color": "violet","score": "150","sprite": ""},
{"x": "598","y": "176","width": "45","height": "23","color": "violet","score": "150","sprite": ""},
{"x": "644","y": "176","width": "45","height": "23","color": "violet","score": "150","sprite": ""},
{"x": "690","y": "176","width": "45","height": "23","color": "violet","score": "150","sprite": ""},
{"x": "736","y": "176","width": "45","height": "23","color": "violet","score": "150","sprite": ""},
{"x": "782","y": "176","width": "45","height": "23","color": "violet","score": "150","sprite": ""},
{"x": "828","y": "176","width": "45","height": "23","color": "violet","score": "150","sprite": ""},
{"x": "874","y": "176","width": "45","height": "23","color": "violet","score": "150","sprite": ""}
  ]
}